[
  {
    "id": "01",
    "title": "BRACNet Support.docx",
    "link": "https://docs.google.com/document/d/1uIJfCckx2wJZXaxXf6l9BidfAkaPb87P/edit?usp=sharing&ouid=114612891558867898297&rtpof=true&sd=true"
  },
  {
    "id": "02",
    "title": "Email Support Template.docx",
    "link": "https://docs.google.com/document/d/1gImugVzSuS_CLgtGDDqlyQ4XHm8HALIk/edit?usp=sharing&ouid=114612891558867898297&rtpof=true&sd=true"
  },
  {
    "id": "03",
    "title": "Laptop Support.docx",
    "link": "https://docs.google.com/document/d/1RTHcXh5NZ5LYZUJ7o1TSz5tPeDxCXQLI/edit?usp=sharing&ouid=114612891558867898297&rtpof=true&sd=true"
  },
  {
    "id": "04",
    "title": "Printer Support.docx",
    "link": "https://docs.google.com/document/d/1diOp0i5kTM1yeUii270gA5e-OcnGeGgk/edit?usp=sharing&ouid=114612891558867898297&rtpof=true&sd=true"
  },
  {
    "id": "05",
    "title": "Trendx Support.docx",
    "link": "https://docs.google.com/document/d/1UiRoUXgN4ITwIKrZs3YHUosz_GiIgVmJ/edit?usp=sharing&ouid=114612891558867898297&rtpof=true&sd=true"
  }
]
